{
	"posts": [
		{
			"link": "https://dev.to/npranto/bfedev-176-undefined-to-null-2fb8",
			"title": "BFE.dev | 176. undefined to null",
			"uploadedTime": "May 21, 2024"
		},
		{
			"link": "https://dev.to/npranto/cssbattle-32-band-aid-3685",
			"title": "CSSBattle | #32 Band-aid",
			"uploadedTime": "May 20, 2024"
		},
		{
			"link": "https://dev.to/npranto/cssbattle-31-equals-70h",
			"title": "CSSBattle | #31 Equals",
			"uploadedTime": "October 16, 2022"
		},
		{
			"link": "https://dev.to/npranto/cssbattle-30-horizon-22gn",
			"title": "CSSBattle | #30 Horizon",
			"uploadedTime": "July 31, 2022"
		},
		{
			"link": "https://dev.to/npranto/cssbattle-29-suffocate-ihk",
			"title": "CSSBattle | #29 Suffocate",
			"uploadedTime": "July 28, 2022"
		},
		{
			"link": "https://dev.to/npranto/cssbattle-28-cups-balls-57h5",
			"title": "CSSBattle | #28 Cups & Balls",
			"uploadedTime": "July 17, 2022"
		},
		{
			"link": "https://dev.to/npranto/cssbattle-27-lock-up-1b70",
			"title": "CSSBattle | #27 Lock Up",
			"uploadedTime": "July 17, 2022"
		},
		{
			"link": "https://dev.to/npranto/cssbattle-26-smiley-3iko",
			"title": "CSSBattle | #26 Smiley",
			"uploadedTime": "July 15, 2022"
		},
		{
			"link": "https://dev.to/npranto/cssbattle-25-blossom-ap3",
			"title": "CSSBattle | #25 Blossom",
			"uploadedTime": "July 12, 2022"
		},
		{
			"link": "https://dev.to/npranto/cssbattle-24-switches-2pl1",
			"title": "CSSBattle | #24 Switches",
			"uploadedTime": "July 12, 2022"
		},
		{
			"link": "https://dev.to/npranto/cssbattle-23-boxception-407o",
			"title": "CSSBattle | #23 Boxception",
			"uploadedTime": "July 5, 2022"
		},
		{
			"link": "https://dev.to/npranto/cssbattle-22-cloud-1536",
			"title": "CSSBattle | #22 Cloud",
			"uploadedTime": "July 4, 2022"
		},
		{
			"link": "https://dev.to/npranto/cssbattle-21-sitepoint-logo-2160",
			"title": "CSSBattle | #21 SitePoint Logo",
			"uploadedTime": "July 2, 2022"
		},
		{
			"link": "https://dev.to/npranto/cssbattle-20-ticket-4ae7",
			"title": "CSSBattle | #20 Ticket",
			"uploadedTime": "July 1, 2022"
		},
		{
			"link": "https://dev.to/npranto/cssbattle-19-cube-3kb2",
			"title": "CSSBattle | #19 Cube",
			"uploadedTime": "July 1, 2022"
		},
		{
			"link": "https://dev.to/npranto/cssbattle-18-matrix-2ga4",
			"title": "CSSBattle | #18 Matrix",
			"uploadedTime": "June 30, 2022"
		},
		{
			"link": "https://dev.to/npranto/cssbattle-17-fidget-spinner-4hl6",
			"title": "CSSBattle | #17 Fidget Spinner",
			"uploadedTime": "April 24, 2022"
		},
		{
			"link": "https://dev.to/npranto/cssbattle-16-eye-of-the-tiger-2df8",
			"title": "CSSBattle | #16 Eye of the Tiger",
			"uploadedTime": "March 17, 2022"
		},
		{
			"link": "https://dev.to/npranto/cssbattle-15-overlap-4i5e",
			"title": "CSSBattle | #15 Overlap",
			"uploadedTime": "March 14, 2022"
		},
		{
			"link": "https://dev.to/npranto/automate-adding-cvs-coupons-p06",
			"title": "Automate Adding CVS Coupons",
			"uploadedTime": "March 12, 2022"
		},
		{
			"link": "https://dev.to/npranto/cssbattle-14-web-maker-logo-47l9",
			"title": "CSSBattle | #14 Web Maker Logo",
			"uploadedTime": "March 9, 2022"
		},
		{
			"link": "https://dev.to/npranto/cssbattle-13-totally-triangle-36pe",
			"title": "CSSBattle | #13 Totally Triangle",
			"uploadedTime": "March 8, 2022"
		},
		{
			"link": "https://dev.to/npranto/cssbattle-12-wiggly-moustache-1noa",
			"title": "CSSBattle | #12 Wiggly Moustache",
			"uploadedTime": "March 7, 2022"
		},
		{
			"link": "https://dev.to/npranto/cssbattle-11-eye-of-sauron-4gch",
			"title": "CSSBattle | #11 Eye of Sauron",
			"uploadedTime": "March 3, 2022"
		},
		{
			"link": "https://dev.to/npranto/cssbattle-10-cloaked-spirits-2bcc",
			"title": "CSSBattle | #10 Cloaked Spirits",
			"uploadedTime": "March 1, 2022"
		},
		{
			"link": "https://dev.to/npranto/cssbattle-9-tesseract-15p9",
			"title": "CSSBattle | #9 Tesseract",
			"uploadedTime": "March 1, 2022"
		},
		{
			"link": "https://dev.to/npranto/cssbattle-8-forking-crazy-52ea",
			"title": "CSSBattle | #8 Forking Crazy",
			"uploadedTime": "March 1, 2022"
		},
		{
			"link": "https://dev.to/npranto/cssbattle-7-leafy-trail-4g86",
			"title": "CSSBattle | #7 Leafy Trail",
			"uploadedTime": "February 28, 2022"
		},
		{
			"link": "https://dev.to/npranto/cssbattle-6-missing-slice-8ip",
			"title": "CSSBattle | #6 Missing Slice",
			"uploadedTime": "February 27, 2022"
		},
		{
			"link": "https://dev.to/npranto/cssbattle-5-acid-rain-3e55",
			"title": "CSSBattle | #5 Acid Rain",
			"uploadedTime": "February 27, 2022"
		},
		{
			"link": "https://dev.to/npranto/cssbattle-4-ups-n-downs-267e",
			"title": "CSSBattle | #4 Ups n Downs",
			"uploadedTime": "February 27, 2022"
		},
		{
			"link": "https://dev.to/npranto/cssbattle-3-push-button-2gg9",
			"title": "CSSBattle | #3 Push Button",
			"uploadedTime": "February 27, 2022"
		},
		{
			"link": "https://dev.to/npranto/cssbattle-2-carrom-4l37",
			"title": "CSSBattle | #2 Carrom",
			"uploadedTime": "February 25, 2022"
		},
		{
			"link": "https://dev.to/npranto/cssbattle-1-simply-square-3j7",
			"title": "CSSBattle | #1 Simply Square",
			"uploadedTime": "February 24, 2022"
		},
		{
			"link": "https://dev.to/npranto/how-i-setup-eslint-prettier-and-editorconfig-for-static-sites-33ep",
			"title": "How I Setup ESLint, Prettier, and EditorConfig for Static Sites",
			"uploadedTime": "January 25, 2022"
		},
		{
			"link": "https://dev.to/npranto/macos-web-development-setup-guide-345p",
			"title": "macOS Web Development Setup Guide",
			"uploadedTime": "December 8, 2021"
		},
		{
			"link": "https://dev.to/npranto/quick-bite-ssh-key-4llh",
			"title": "Quick Bite: SSH Key",
			"uploadedTime": "December 4, 2021"
		}
	]
}
